{
	"name":"getFileFromPath",
	"type":"function",
	"syntax":"getFileFromPath(path)",
	"returns":"string",
	"related":["getDirectoryFromPath"],
	"description":" Extracts a filename from an absolute path.",
	"params": [
		{"name":"path","description":"","required":true,"default":"","type":"string","values":[]}
	],
	"engines": {
		"coldfusion": {"minimum_version":"", "notes":"", "docs":"https://helpx.adobe.com/coldfusion/cfml-reference/coldfusion-functions/functions-e-g/getfilefrompath.html"},
		"lucee": {"minimum_version":"", "notes":"", "docs":"https://docs.lucee.org/reference/functions/getfilefrompath.html"},
		"railo": {"minimum_version":"", "notes":"", "docs":"http://railodocs.org/index.cfm/function/getfilefrompath"},
		"openbd": {"minimum_version":"", "notes":"", "docs":"http://openbd.org/manual/?/function/getfilefrompath"}
	},
	"links": [],
	"examples" : [
		{
			"title":"Basic Example",
			"description":"",
			"code":"getFileFromPath(\"C:\\temp\\file.txt\")",
			"result":"file.txt",
			"runnable":true
		}
	]
}
