{
    "engines": {"lucee": {
        "docs": "https://docs.lucee.org/reference/functions/GetSystemPropOrEnvVar.html",
        "minimum_version": "6.2"
    }},
    "name": "GetSystemPropOrEnvVar",
    "description": "Return the list of supported system properties or env vars Lucee supports.",
    "syntax": "GetSystemPropOrEnvVar(  )",
    "returns": "any",
    "type": "function",
    "params": [{
        "name": "property",
        "description": "Optional, when set, the value of the property as configured is returned",
        "type": "string",
        "required": false
    }]
}