{
	"name":"isNumeric",
	"type":"function",
	"syntax":"isNumeric(String)",
	"returns":"boolean",
	"related":["isValid"],
	"description":"Determines whether a string can be converted to a numeric value. Supports numbers in U.S. number format. For other number support use LSIsNumeric.",
	"params": [
		{"name":"String","description":"","required":true,"default":"","type":"string","values":[]}

	],
	"engines": {
		"coldfusion": {"minimum_version":"", "notes":"", "docs":"https://helpx.adobe.com/coldfusion/cfml-reference/coldfusion-functions/functions-in-k/isnumeric.html"},
		"lucee": {"minimum_version":"", "notes":"", "docs":"https://docs.lucee.org/reference/functions/isnumeric.html"},
		"railo": {"minimum_version":"", "notes":"", "docs":"http://railodocs.org/index.cfm/function/isnumeric"},
		"openbd": {"minimum_version":"", "notes":"", "docs":"http://openbd.org/manual/?/function/isnumeric"}
	},
	"links": [

	],
	"examples": [
		{
			"title":"Integer isNumeric",
			"description":"",
			"code":"isNumeric(23)",
			"result":"YES"
		},
		{
			"title":"String isNumeric",
			"description":"",
			"code":"isNumeric(\"twenty\")",
			"result":"NO"
		},
		{
			"title":"Scientific Notation",
			"description":"The number `5e2` is scientific notation for `5 x 10^2` aka `500`",
			"code":"isNumeric(5e2)",
			"result":"YES"
		}
	]

}
