{
    "name":"isSafeHTML",
    "syntax":"isSafeHTML(inputString [, PolicyFile])",
    "returns":"boolean",
    "type":"function",
    "related":["getSafeHTML"],
    "description":"Checks a HTML string against antisamy policy file to determine if it may be vulnerable to XSS / Cross Site Scripting.",
    "engines":{
        "coldfusion":{"minimum_version":"11","docs":"https://helpx.adobe.com/coldfusion/cfml-reference/coldfusion-functions/functions-in-k/issafehtml.html","notes":""}
    },

    "links":[
        {"title":"AntiSamy OWASP","description":"","url":"https://www.owasp.org/index.php/Category:OWASP_AntiSamy_Project"}
    ],
    "params":[
        {"values":[],"default":"","description":"String to be validated","name":"inputString","type":"string","required":true},
        {"values":[],"default":"","description":"File path for custom AntiSamy policy file. Can be defined in the application scope or if not defined will use ColdFusion server default","name":"PolicyFile","type":"string","required":false}
    ],
    "examples":[
        {"result":"no","title":"Unsafe HTML Example","description":"Example with HTML that causes isSafeHTML to return false.","code":"<cfsavecontent variable=\"html\">\r\n    <div onmouseover=alert(1)>\r\n</cfsavecontent>\r\n<cfoutput>#isSafeHTML(html)#</cfoutput>"},
        {"result":"yes","title":"Safe HTML Example","description":"Example with HTML that is safe on the default policy.","code":"<cfsavecontent variable=\"html\">\r\n    <a href=\"https://foundeo.com/\" title=\"ColdFusion Consulting &amp; Security\">Foundeo Inc.</a>\r\n</cfsavecontent>\r\n<cfoutput>#isSafeHTML(html)#</cfoutput>"}
    ]

}
