{
	"name":"isValidOauthAccesstoken",
	"type":"function",
	"syntax":"isValidOauthAccesstoken(token,type);",
	"returns":"boolean",
	"related":[],
	"description":"Checks if the OAuth access token is still valid.",
	"params": [
		{"name":"token","description":"The access token to check.","required":true,"default":"","type":"","values":[]},
		{"name":"type","description":"The type of the OAuth server (facebook/google).","required":true,"default":"","type":"","values":[]}
	],
	"engines": {
		"coldfusion": {"minimum_version":"11", "notes":"", "docs":"https://helpx.adobe.com/coldfusion/cfml-reference/coldfusion-functions/functions-in-k/isvalidoauthaccesstoken.html"}
	},
	"links": [

	],
	"examples": [
		{
			"title": "Tag Syntax",
			"description": "",
			"code": "isValidOauthAccesstoken(\"any_token_value\",\"facebook\") \r\n",
			"result": ""
		}
	]

}