{
	"name":"lJustify",
	"type":"function",
	"syntax":"lJustify(String, length)",
	"returns":"string",
	"related":["rJustify","cJustify"],
	"description":" Left justifies characters in a string of a specified length.",
	"params": [
		{"name":"String","description":"","required":true,"default":"","type":"string","values":[]},
		{"name":"length","description":"","required":true,"default":"","type":"numeric","values":[]}

	],
	"engines": {
		"coldfusion": {"minimum_version":"", "notes":"", "docs":"https://helpx.adobe.com/coldfusion/cfml-reference/coldfusion-functions/functions-l/ljustify.html"},
		"lucee": {"minimum_version":"", "notes":"", "docs":"https://docs.lucee.org/reference/functions/ljustify.html"},
		"railo": {"minimum_version":"", "notes":"", "docs":"http://railodocs.org/index.cfm/function/ljustify"},
		"openbd": {"minimum_version":"", "notes":"", "docs":"http://openbd.org/manual/?/function/ljustify"}
	},
	"links": [
		{
			"title":"Learning lJustify by Ben Nadel",
			"url":"https://www.bennadel.com/blog/1421-ask-ben-creating-a-fixed-field-width-data-file-with-coldfusion.htm",
			"description":"lJustify function in CFML."
		}
	],
	"examples": [
		{
			"title":"Tag Example",
			"description":" ",
			"code":"<cfset length=10>\r\n<cfset result = LJustify(\"abc\",length)>\r\n<cfoutput>\r\n    <pre>~#result#~</pre>\r\n</cfoutput>",
			"result":"",
			"runnable":true
		}
	]

}
