{
	"name":"spreadsheetSetCellValue",
	"type":"function",
	"syntax":"spreadsheetSetCellValue(spreadsheetObj, value, row, column)",
	"returns":"void",
	"related":[],
	"description":" Specifies the value of an Excel spreadsheet object cell.",
	"params": [
		{"name":"spreadsheetObj","description":"No Help Available","required":true,"default":"","type":"variableName","values":[]},
		{"name":"value","description":"No Help Available","required":true,"default":"","type":"string","values":[]},
		{"name":"row","description":"No Help Available","required":true,"default":"","type":"numeric","values":[]},
		{"name":"column","description":"No Help Available","required":true,"default":"","type":"numeric","values":[]}

	],
	"engines": {
		"coldfusion": {"minimum_version":"", "notes":"", "docs":"https://helpx.adobe.com/coldfusion/cfml-reference/coldfusion-functions/functions-s/spreadsheetsetcellvalue.html"},
		"openbd": {"minimum_version":"", "notes":"", "docs":"http://openbd.org/manual/?/function/spreadsheetsetcellvalue"}
	},
	"links": [

	],
	"examples": [
		{
			"title":"Script Example",
			"description":" ",
			"code":"<cfset q = queryNew(\"Name,Beers,Vegetables,Fruits,Meats\", \"cf_sql_varchar,cf_sql_integer,cf_sql_integer,cf_sql_integer,cf_sql_integer\")> \r\n  <cfset queryAddRow(q)> \r\n  <cfset querySetCell(q, \"Name\", \"John\")> \r\n  <cfset querySetCell(q, \"Beers\", \"1\")> \r\n  <cfset querySetCell(q, \"Vegetables\", \"1\")> \r\n  <cfset querySetCell(q, \"Fruits\", \"1\")> \r\n  <cfset querySetCell(q, \"Meats\", \"1\")> \r\n  <cfset mySheet =   SpreadsheetNew( \"Test\"  ) /> \r\n  <!--- Make a spreadsheet object ---> \r\n  <cfset s = spreadsheetNew()> \r\n  <!--- Add header row ---> \r\n  <cfset spreadsheetAddRow(s, \"Name,Beers,Vegetables,Fruits,Meats\")> \r\n  <!--- Add query ---> \r\n   <cfscript> \r\n  spreadsheetSetCellValue(s, 111, 2,1); \r\n theFormula=SpreadsheetGetCellValue(s,2,1); \r\n </cfscript> \r\n <cfoutput> \r\n Row,Column: #theFormula# \r\n </cfoutput>  ",
			"result":"",
			"runnable":true
		}
	]

}
