{
	"name":"spreadsheetFormatColumn",
	"type":"function",
	"syntax":"spreadsheetFormatColumn(spreadsheetObj, format, column)",
	"returns":"void",
	"related":[],
	"description":" Formats the contents of a single column of an Excel spreadsheet object.",
	"params": [
		{"name":"spreadsheetObj","description":"No Help Available","required":true,"default":"","type":"Variablename","values":[]},
		{"name":"format","description":"No Help Available","required":true,"default":"","type":"String","values":[]},
		{"name":"column","description":"No Help Available","required":true,"default":"","type":"Numeric","values":[]}

	],
	"engines": {
		"coldfusion": {"minimum_version":"", "notes":"", "docs":"http://learn.adobe.com/wiki/display/coldfusionen/spreadsheetformatcolumn"},
		"railo": {"minimum_version":"", "notes":"", "docs":"http://railodocs.org/index.cfm/function/spreadsheetformatcolumn"},
		"openbd": {"minimum_version":"", "notes":"", "docs":"http://openbd.org/manual/?/function/spreadsheetformatcolumn"}
	},
	"links": [

	]

}
